cli_sender/__init__.py
cli_sender/main.py
clisender/__init__.py
clisender/main.py
cli_sender-0.0.3.dist-info/LICENSE
cli_sender-0.0.3.dist-info/METADATA
cli_sender-0.0.3.dist-info/WHEEL
cli_sender-0.0.3.dist-info/top_level.txt
cli_sender-0.0.3.dist-info/RECORD
